{
  "pools": [
    {
      "rolls": 1,
      "entries": [
        {
          "type": "minecraft:item",
          "name": "minecraft:poisonous_potato",
          "functions": [
            {
              "function": "minecraft:set_components",
              "components": {
                "minecraft:item_name": {"translate":"item.spiced.music_disc_green_regime","fallback":"Music Disc"},
                "minecraft:item_model": "spiced:music_disc_green_regime",
                "minecraft:custom_data": {"spiced":{"disc":{"type":"green_regime"}},"smithed":{"ignore":{"functionality":true,"crafting":true}}},
                "minecraft:lore": [{"translate":"spiced.tooltip","font":"spiced:tooltip","color":"white","italic":false}],
                "minecraft:rarity": "uncommon",
                "minecraft:jukebox_playable": "spiced:green_regime",
                "!minecraft:consumable": {},
                "minecraft:max_stack_size": 1
              }
            }
          ]
        }
      ]
    }
  ]
}